geniussis_api_fr8train/__init__.py
geniussis_api_fr8train/api.py
geniussis_api_fr8train/factories/__init__.py
geniussis_api_fr8train/factories/authentication.py
geniussis_api_fr8train/models/__init__.py
geniussis_api_fr8train/models/connection.py
geniussis_api_fr8train-0.1.0.dist-info/licenses/LICENSE
geniussis_api_fr8train-0.1.0.dist-info/METADATA
geniussis_api_fr8train-0.1.0.dist-info/WHEEL
geniussis_api_fr8train-0.1.0.dist-info/top_level.txt
geniussis_api_fr8train-0.1.0.dist-info/RECORD
