Metadata-Version: 2.4
Name: geniussis-api-fr8train
Version: 0.1.0
Summary: A Python SDK for integrating with the GeniusSIS API
Author-email: Tyler Collette <tyler.collette@gmail.com>
Project-URL: Documentation, https://github.com/fr8train-sv/geniussis-api/wiki
Project-URL: Source, https://github.com/fr8train-sv/geniussis-api
Project-URL: Changelog, https://github.com/fr8train-sv/geniussis-api/releases
Keywords: genius,api,sdk,geniussis,integration
Classifier: Programming Language :: Python :: 3
Classifier: Programming Language :: Python :: 3.12
Classifier: Operating System :: OS Independent
License-File: LICENSE
Requires-Dist: requests
Requires-Dist: dotenv
Requires-Dist: python-dotenv
Dynamic: license-file
